pyupdater_http/__init__.py
pyupdater_http/uploader.py
pyupdater_http-0.7.0.dist-info/entry_points.txt
pyupdater_http-0.7.0.dist-info/WHEEL
pyupdater_http-0.7.0.dist-info/METADATA
pyupdater_http-0.7.0.dist-info/RECORD
