Metadata-Version: 2.1
Name: pyupdater-http
Version: 0.7.0
Summary: PyUpdater Plugin: HTTP upload support
Home-page: https://github.com/micro-fan/pyupdater-http
Keywords: pyupdater,pyupdater-plugin,http
Author: Kirill Pinchuk
Author-email: cybergrind@gmail.com
Requires-Python: >=3.7
Classifier: Programming Language :: Python :: 3
Classifier: Programming Language :: Python :: 3.7
Classifier: Programming Language :: Python :: 3.8
Classifier: Programming Language :: Python :: 3.9
Classifier: Programming Language :: Python :: 3.10
Classifier: Programming Language :: Python :: 3.11
Requires-Dist: httpx (>=0.23.0)
Project-URL: Repository, https://github.com/micro-fan/pyupdater-http
